shy_sentry/__init__.py
shy_sentry/shy_sentry.py
shy_sentry-1.2.0.dist-info/LICENSE
shy_sentry-1.2.0.dist-info/METADATA
shy_sentry-1.2.0.dist-info/WHEEL
shy_sentry-1.2.0.dist-info/top_level.txt
shy_sentry-1.2.0.dist-info/RECORD
