Metadata-Version: 2.1
Name: shy-sentry
Version: 1.2.0
Summary: sentry-sdk but quite
Home-page: https://github.com/arrai-innovations/shy-sentry/
Author: Arrai Innovations
Author-email: support@arrai.com
License: LICENSE
Platform: UNKNOWN
Classifier: Development Status :: 4 - Beta
Classifier: Programming Language :: Python :: 3
Classifier: Programming Language :: Python :: 3.6
Classifier: Programming Language :: Python :: 3.7
Classifier: Programming Language :: Python :: 3.8
Classifier: License :: OSI Approved :: BSD License
Classifier: Intended Audience :: Developers
Requires-Dist: setuptools (>=45.1.0)
Requires-Dist: sentry-sdk (<1.0.0,>=0.14.1)
